autora/runner/recruitment_manager/prolific/__init__.py
autora_runner_recruitment_manager_prolific-0.1.0.dist-info/METADATA
autora_runner_recruitment_manager_prolific-0.1.0.dist-info/WHEEL
autora_runner_recruitment_manager_prolific-0.1.0.dist-info/top_level.txt
autora_runner_recruitment_manager_prolific-0.1.0.dist-info/RECORD
