Metadata-Version: 2.1
Name: autora-runner-recruitment-manager-prolific
Version: 0.1.0
Summary: AutoRA prolific recruitment manager provides functionality to recruite participants via Prolific to setup an experiment runner for AutoRA
Author-email: Kevin Phan <kphan@princeton.edu>, Younes Strittmatter <younes_strittmatter@brown.edu>
License: MIT License
Project-URL: homepage, http://www.empiricalresearch.ai
Project-URL: repository, https://github.com/AutoResearch/autora-runner-recruitment-manager-prolific
Project-URL: documentation, https://autoresearch.github.io/autora/
Requires-Python: <4,>=3.8
Requires-Dist: autora-core
Provides-Extra: dev
Requires-Dist: autora-core[dev] ; extra == 'dev'
